AskQuora-0.2.7.dist-info/DESCRIPTION.rst
AskQuora-0.2.7.dist-info/METADATA
AskQuora-0.2.7.dist-info/RECORD
AskQuora-0.2.7.dist-info/WHEEL
AskQuora-0.2.7.dist-info/entry_points.txt
AskQuora-0.2.7.dist-info/metadata.json
AskQuora-0.2.7.dist-info/top_level.txt
askquora/__init__.py
askquora/askquora.py
