Metadata-Version: 2.0
Name: AskQuora
Version: 0.2.7
Summary: Quora Q&A right from the command line
Home-page: https://www.github.com/Ritiek/AskQuora
Author: Ritiek Malhotra
Author-email: ritiekmalhotra123@gmail.com
License: MIT
Download-URL: https://github.com/Ritiek/AskQuora/archive/v0.2.7.tar.gz
Keywords: quora,terminal,command-line,question,python
Platform: UNKNOWN
Requires-Dist: BeautifulSoup4
Requires-Dist: colorama
Requires-Dist: requests
Requires-Dist: requests-cache
